vmaker/__init__.py
vmaker/constants.py
vmaker/funcs.py
vmaker/main.py
vmaker/utils.py
vmaker-0.1.2.dist-info/entry_points.txt
vmaker-0.1.2.dist-info/METADATA
vmaker-0.1.2.dist-info/WHEEL
vmaker-0.1.2.dist-info/RECORD
