Metadata-Version: 2.1
Name: vmaker
Version: 0.1.2
Summary: 
Author: gaojunran
Author-email: nebula2021@126.com
Requires-Python: >=3.8,<4.0
Classifier: Programming Language :: Python :: 3
Classifier: Programming Language :: Python :: 3.8
Classifier: Programming Language :: Python :: 3.9
Classifier: Programming Language :: Python :: 3.10
Classifier: Programming Language :: Python :: 3.11
Classifier: Programming Language :: Python :: 3.12
Requires-Dist: ffmpeg-python (>=0.2.0,<0.3.0)
Requires-Dist: typer[all] (>=0.12.3,<0.13.0)
